starlette_graphene3.py
starlette_graphene3-0.5.1.dist-info/LICENSE.txt
starlette_graphene3-0.5.1.dist-info/WHEEL
starlette_graphene3-0.5.1.dist-info/METADATA
starlette_graphene3-0.5.1.dist-info/RECORD
