Metadata-Version: 2.1
Name: starlette-graphene3
Version: 0.5.1
Summary: Use Graphene v3 on Starlette
Home-page: https://github.com/ciscorn/starlette-graphene3
License: MIT
Keywords: graphene,graphql,asgi,starlette
Author: Taku Fukada
Author-email: naninunenor@gmail.com
Requires-Python: >=3.7,<4.0
Classifier: License :: OSI Approved :: MIT License
Classifier: Operating System :: OS Independent
Classifier: Programming Language :: Python :: 3
Classifier: Programming Language :: Python :: 3.7
Classifier: Programming Language :: Python :: 3.8
Classifier: Programming Language :: Python :: 3.9
Classifier: Topic :: Internet :: WWW/HTTP
Classifier: Topic :: Software Development :: Libraries :: Python Modules
Requires-Dist: graphene (>=3.0b6)
Requires-Dist: starlette (>=0.14.1)
Project-URL: Repository, https://github.com/ciscorn/starlette-graphene3
